ConformalImpact/Model.py
ConformalImpact/__init__.py
ConformalImpact-0.0.3.dist-info/LICENSE
ConformalImpact-0.0.3.dist-info/METADATA
ConformalImpact-0.0.3.dist-info/WHEEL
ConformalImpact-0.0.3.dist-info/top_level.txt
ConformalImpact-0.0.3.dist-info/RECORD
