Metadata-Version: 2.1
Name: ConformalImpact
Version: 0.0.3
Summary: Confrmal Based Impact Analysis.
Home-page: https://github.com/tblume1992/ConformalImpact
Author: Tyler Blume
Keywords: forecasting,time series,seasonality,trend
Classifier: Programming Language :: Python :: 3
Classifier: License :: OSI Approved :: MIT License
Classifier: Operating System :: OS Independent
License-File: LICENSE
Requires-Dist: numpy
Requires-Dist: pandas
Requires-Dist: tqdm
Requires-Dist: numba
Requires-Dist: matplotlib
Requires-Dist: mfles
